tf/records/__init__.py
tf/records/__init__.pyi
tf/records/dataset.py
tf/records/examples.py
tf/records/io.py
tf/records/meta.py
tf/records/sharding.py
tensorflow_records-0.1.14.dist-info/METADATA
tensorflow_records-0.1.14.dist-info/WHEEL
tensorflow_records-0.1.14.dist-info/top_level.txt
tensorflow_records-0.1.14.dist-info/RECORD
