Metadata-Version: 2.1
Name: tensorflow-records
Version: 0.1.14
Summary: Simple standard + tools for I/O of TFRecords
Author-email: Marcel Claramunt <marcel@moveread.com>
Project-URL: repo, https://github.com/moveread/tensorflow-ocr.git
Requires-Python: >=3.10
Requires-Dist: pydantic
Requires-Dist: tensorflow
Requires-Dist: tf-tools
Requires-Dist: fs-tools
